<?xml version="1.0" encoding="UTF-8"?>
<panel version="14">
 <properties>
  <prop name="Name">
   <prop name="en_US.utf8"></prop>
   <prop name="zh_CN.utf8"></prop>
  </prop>
  <prop name="Size">1356 799</prop>
  <prop name="BackColor">_3DFace</prop>
  <prop name="RefPoint">70 85</prop>
  <prop name="InitAndTermRef">True</prop>
  <prop name="SendClick">False</prop>
  <prop name="RefFileName"></prop>
  <prop name="DPI">120</prop>
  <prop name="layoutType">None</prop>
 </properties>
 <shapes>
  <shape Name="TAB1" shapeType="TAB" layerId="0">
   <properties>
    <prop name="serialId">62</prop>
    <prop name="Type"></prop>
    <prop name="RefPoint">15 10</prop>
    <prop name="Enable">True</prop>
    <prop name="Visible">True</prop>
    <prop name="ForeColor">_3DText</prop>
    <prop name="BackColor">_3DFace</prop>
    <prop name="TabOrder">61</prop>
    <prop name="ToolTipText">
     <prop name="en_US.utf8"></prop>
     <prop name="zh_CN.utf8"></prop>
    </prop>
    <prop name="layoutAlignment">AlignNone</prop>
    <prop name="snapMode">Point</prop>
    <prop name="Font">
     <prop name="en_US.utf8">Segoe UI,-1,12,5,50,0,0,0,0,0</prop>
     <prop name="zh_CN.utf8">Segoe UI,-1,12,5,50,0,0,0,0,0</prop>
    </prop>
    <prop name="Location">15 10</prop>
    <prop name="Size">1331 786</prop>
    <prop name="TabBarAutoHide">False</prop>
    <prop name="Page">
     <prop name="Name">#1</prop>
     <prop name="Label">
      <prop name="en_US.utf8">#1</prop>
      <prop name="zh_CN.utf8">SPC点位管理</prop>
     </prop>
     <prop name="Panel">SPC/SPC_TABLE.xml</prop>
    </prop>
    <prop name="Page">
     <prop name="Name">#2</prop>
     <prop name="Label">
      <prop name="en_US.utf8">#2</prop>
      <prop name="zh_CN.utf8">子系统管理</prop>
     </prop>
     <prop name="Panel">SPC/SUBSYSTEM.xml</prop>
    </prop>
    <prop name="Page">
     <prop name="Name">#3</prop>
     <prop name="Label">
      <prop name="en_US.utf8">#3</prop>
      <prop name="zh_CN.utf8">课别管理</prop>
     </prop>
     <prop name="Panel">SPC/DEPARTMENT.xml</prop>
    </prop>
    <prop name="Page">
     <prop name="Name">SPC导点工具</prop>
     <prop name="Label">
      <prop name="en_US.utf8">#4</prop>
      <prop name="zh_CN.utf8">SPC导点工具</prop>
     </prop>
     <prop name="Panel">SPC/SPC倒点工具.xml</prop>
    </prop>
   </properties>
  </shape>
 </shapes>
</panel>
